{
  "directed": true,
  "multigraph": false,
  "graph": {},
  "nodes": [
    {
      "label": "message",
      "text": "Hi Person1, Just checking to see how my bloodwork looks for my WBC? Thanks Person2",
      "id": 39
    },
    {
      "label": "sentence",
      "text": "Hi Person1, Just checking to see how my bloodwork looks for my WBC?",
      "id": "39_0"
    },
    {
      "label": "subsentence",
      "text": "Hi Person1,",
      "id": "39_0_0"
    },
    {
      "label": "subsentence",
      "text": "Just checking to see how my bloodwork looks",
      "id": "39_0_1"
    },
    {
      "label": "subsentence",
      "text": "for my WBC?",
      "id": "39_0_2"
    },
    {
      "label": "sentence",
      "text": "Thanks Person2",
      "id": "39_1"
    },
    {
      "label": "subsentence",
      "text": "Thanks Person2",
      "id": "39_1_0"
    }
  ],
  "links": [
    {
      "source": 39,
      "target": "39_0"
    },
    {
      "source": 39,
      "target": "39_1"
    },
    {
      "source": "39_0",
      "target": "39_0_0"
    },
    {
      "source": "39_0",
      "target": "39_0_1"
    },
    {
      "source": "39_0",
      "target": "39_0_2"
    },
    {
      "source": "39_1",
      "target": "39_1_0"
    }
  ]
}