{
  "directed": true,
  "multigraph": false,
  "graph": {},
  "nodes": [
    {
      "label": "message",
      "text": "Good Morning Mr. Person1, The PSA is still in progress and the result will be available on My Chart once completed.",
      "id": 319
    },
    {
      "label": "sentence",
      "text": "Good Morning Mr. Person1, The PSA is still in progress and the result will be available on My Chart once completed.",
      "id": "319_0"
    },
    {
      "label": "subsentence",
      "text": "Good Morning Mr. Person1,",
      "id": "319_0_0"
    },
    {
      "label": "subsentence",
      "text": "The PSA is still in progress and the result will be",
      "id": "319_0_1"
    },
    {
      "label": "subsentence",
      "text": "available on My Chart once completed",
      "id": "319_0_2"
    }
  ],
  "links": [
    {
      "source": 319,
      "target": "319_0"
    },
    {
      "source": "319_0",
      "target": "319_0_0"
    },
    {
      "source": "319_0",
      "target": "319_0_1"
    },
    {
      "source": "319_0",
      "target": "319_0_2"
    }
  ]
}