{
  "directed": true,
  "multigraph": false,
  "graph": {},
  "nodes": [
    {
      "label": "I",
      "pos": "PRON",
      "id": 0
    },
    {
      "label": "will",
      "pos": "AUX",
      "id": 1
    },
    {
      "label": "add",
      "pos": "VERB",
      "id": 2
    },
    {
      "label": "you",
      "pos": "PRON",
      "id": 3
    },
    {
      "label": "on",
      "pos": "ADP",
      "id": 4
    },
    {
      "label": "MM",
      "pos": "PROPN",
      "id": 5
    },
    {
      "label": "/",
      "pos": "SYM",
      "id": 6
    },
    {
      "label": "DD",
      "pos": "PROPN",
      "id": 7
    },
    {
      "label": "/",
      "pos": "SYM",
      "id": 8
    },
    {
      "label": "YYYY",
      "pos": "PROPN",
      "id": 9
    },
    {
      "label": "when",
      "pos": "SCONJ",
      "id": 10
    },
    {
      "label": "you",
      "pos": "PRON",
      "id": 11
    },
    {
      "label": "come",
      "pos": "VERB",
      "id": 12
    },
    {
      "label": "to",
      "pos": "PART",
      "id": 13
    },
    {
      "label": "Org2",
      "pos": "VERB",
      "id": 14
    },
    {
      "label": "to",
      "pos": "PART",
      "id": 15
    },
    {
      "label": "see",
      "pos": "VERB",
      "id": 16
    },
    {
      "label": "Dr.",
      "pos": "PROPN",
      "id": 17
    },
    {
      "label": "Person1",
      "pos": "PROPN",
      "id": 18
    },
    {
      "label": ".",
      "pos": "PUNCT",
      "id": 19
    }
  ],
  "links": [
    {
      "dep": "nsubj",
      "source": 2,
      "target": 0
    },
    {
      "dep": "aux",
      "source": 2,
      "target": 1
    },
    {
      "dep": "dobj",
      "source": 2,
      "target": 3
    },
    {
      "dep": "prep",
      "source": 2,
      "target": 4
    },
    {
      "dep": "advcl",
      "source": 2,
      "target": 12
    },
    {
      "dep": "punct",
      "source": 2,
      "target": 19
    },
    {
      "dep": "pobj",
      "source": 4,
      "target": 9
    },
    {
      "dep": "punct",
      "source": 7,
      "target": 6
    },
    {
      "dep": "nmod",
      "source": 9,
      "target": 5
    },
    {
      "dep": "nmod",
      "source": 9,
      "target": 7
    },
    {
      "dep": "punct",
      "source": 9,
      "target": 8
    },
    {
      "dep": "advmod",
      "source": 12,
      "target": 10
    },
    {
      "dep": "nsubj",
      "source": 12,
      "target": 11
    },
    {
      "dep": "advcl",
      "source": 12,
      "target": 14
    },
    {
      "dep": "advcl",
      "source": 12,
      "target": 16
    },
    {
      "dep": "aux",
      "source": 14,
      "target": 13
    },
    {
      "dep": "aux",
      "source": 16,
      "target": 15
    },
    {
      "dep": "dobj",
      "source": 16,
      "target": 18
    },
    {
      "dep": "compound",
      "source": 18,
      "target": 17
    }
  ]
}