{
  "directed": true,
  "multigraph": false,
  "graph": {},
  "nodes": [
    {
      "label": "prior",
      "pos": "ADV",
      "id": 0
    },
    {
      "label": "to",
      "pos": "ADP",
      "id": 1
    },
    {
      "label": "my",
      "pos": "PRON",
      "id": 2
    },
    {
      "label": "visit",
      "pos": "NOUN",
      "id": 11
    },
    {
      "label": "upcoming",
      "pos": "ADJ",
      "id": 3
    },
    {
      "label": "(",
      "pos": "PUNCT",
      "id": 4
    },
    {
      "label": "YYYY",
      "pos": "PROPN",
      "id": 9
    },
    {
      "label": "MM",
      "pos": "PROPN",
      "id": 5
    },
    {
      "label": "/",
      "pos": "SYM",
      "id": 6
    },
    {
      "label": "DD",
      "pos": "PROPN",
      "id": 7
    },
    {
      "label": "/",
      "pos": "SYM",
      "id": 8
    },
    {
      "label": ")",
      "pos": "PUNCT",
      "id": 10
    },
    {
      "label": ".",
      "pos": "PUNCT",
      "id": 12
    }
  ],
  "links": [
    {
      "dep": "prep",
      "source": 0,
      "target": 1
    },
    {
      "dep": "punct",
      "source": 0,
      "target": 12
    },
    {
      "dep": "pobj",
      "source": 1,
      "target": 11
    },
    {
      "dep": "poss",
      "source": 11,
      "target": 2
    },
    {
      "dep": "nmod",
      "source": 11,
      "target": 3
    },
    {
      "dep": "punct",
      "source": 11,
      "target": 10
    },
    {
      "dep": "appos",
      "source": 3,
      "target": 9
    },
    {
      "dep": "punct",
      "source": 9,
      "target": 4
    },
    {
      "dep": "nmod",
      "source": 9,
      "target": 5
    },
    {
      "dep": "punct",
      "source": 9,
      "target": 6
    },
    {
      "dep": "nmod",
      "source": 9,
      "target": 7
    },
    {
      "dep": "punct",
      "source": 9,
      "target": 8
    }
  ]
}