{
  "directed": true,
  "multigraph": false,
  "graph": {},
  "nodes": [
    {
      "label": "a",
      "pos": "DET",
      "id": 0
    },
    {
      "label": "plan",
      "pos": "NOUN",
      "id": 3
    },
    {
      "label": "new",
      "pos": "ADJ",
      "id": 1
    },
    {
      "label": "treatment",
      "pos": "NOUN",
      "id": 2
    },
    {
      "label": ".",
      "pos": "PUNCT",
      "id": 4
    }
  ],
  "links": [
    {
      "dep": "det",
      "source": 3,
      "target": 0
    },
    {
      "dep": "amod",
      "source": 3,
      "target": 1
    },
    {
      "dep": "compound",
      "source": 3,
      "target": 2
    },
    {
      "dep": "punct",
      "source": 3,
      "target": 4
    }
  ]
}